README.md
setup.py
zoom_toolkit/__init__.py
zoom_toolkit/face_remove.py
zoom_toolkit/scene_detector.py
zoom_toolkit/silencecut.py
zoom_toolkit.egg-info/PKG-INFO
zoom_toolkit.egg-info/SOURCES.txt
zoom_toolkit.egg-info/dependency_links.txt
zoom_toolkit.egg-info/requires.txt
zoom_toolkit.egg-info/top_level.txt